Workbook

Sheet Inputs
A1: First Apartment Cost Comparator
A3: Instructions: | B3: Enter details for up to 3 apartments. The tool will compare total monthly and annual costs, including utilities.
A5: General Assumptions
A6: Average monthly groceries | B6: 300
A7: Average monthly transportation | B7: 150
A8: Average internet/cable | B8: 60
B10: Apartment 1 | C10: Apartment 2 | D10: Apartment 3
A11: Category
A12: Apartment Name/Location | B12: The Henry/Tampa | C12: Arabelle Riverwalk/Tampa | D12: The Metropolitan/Tampa
A13: Monthly Rent (1 bed, 1 bath) | B13: 2839 | C13: 2414 | D13: 1945
A14: Utilities Included? (Yes/No) | B14: No | C14: No | D14: No
A15: Estimated Electric (if No) | B15: 80 | C15: 80 | D15: 80
A16: Estimated Water/Trash (if No) | B16: 40 | C16: 60 | D16: 45.5
A17: Estimated Gas (if No) | B17: 0 | C17: 0 | D17: 0
A18: Square Footage (optional) | B18: 499 sqft | C18: 801 sqft | D18: 549 sqft

Sheet Calculations
A1: Label | B1: Apartment 1 | C1: Apartment 2 | D1: Apartment 3
A2: Total Utilities | B2: =IF(Inputs!B14="Yes",0,SUM(Inputs!B15:B17)) -> 120 | C2: =IF(Inputs!C14="Yes",0,SUM(Inputs!C15:C17)) -> 140 | D2: =IF(Inputs!D14="Yes",0,SUM(Inputs!D15:D17)) -> 125.5
A3: Total Monthly Cost | B3: =Inputs!B13 + B2 + 300 + 150 + 60 -> 3469 | C3: =Inputs!C13 + C2 + 300 + 150 + 60 -> 3064 | D3: =Inputs!D13 + D2 + 300 + 150 + 60 -> 2580.5
A4: Total Annual Cost | B4: =B3*12 -> 41628 | C4: =C3*12 -> 36768 | D4: =D3*12 -> 30966
A5: Difference vs Cheapest | B5: =B3 - MIN($B$3:$D$3) -> 888.5 | C5: =C3 - MIN($B$3:$D$3) -> 483.5 | D5: =D3 - MIN($B$3:$D$3) -> 0

Sheet Summary & Charts
A1: First Apartment Budget Comparator - Results
A2: Content | B2: Apartment 1 | C2: Apartment 2 | D2: Apartment 3 | F2: Expense Breakdown - Apartment 3
A3: Total Monthly Cost | B3: =Calculations!B3 -> 3469 | C3: =Calculations!C3 -> 3064 | D3: =Calculations!D3 -> 2580.5 | F3: Rent | G3: =Inputs!D13 -> 1945
A4: +10% Rent Increase | B4: =B3*1.1 -> 3815.9 | C4: =C3*1.1 -> 3370.4 | D4: =D3*1.1 -> 2838.55 | F4: Utilities | G4: =Calculations!D2 -> 125.5
A5: Total Annual Cost | B5: =Calculations!B4 -> 41628 | C5: =Calculations!C4 -> 36768 | D5: =Calculations!D4 -> 30966 | F5: Groceries | G5: =Inputs!$B$6 -> 300
A7: Cheapest Option: | B7: =INDEX(B2:D2,MATCH(MIN(B3:D3),B3:D3,0)) -> Apartment 3
A8: Cheapest Monthly Cost: | B8: =MIN(B3:D3) -> 2580.5
A10: Apartment 1
A11: Expense | B11: Amount
A12: Rent | B12: =Inputs!B13 -> 2839
A13: Utilities | B13: =Calculations!B2 -> 120
A14: Groceries | B14: 300
A15: Tranport | B15: 150
A16: Internet | B16: 60
A18: Apartment 2
A19: Expense | B19: Amount
A20: Rent | B20: =Inputs!C13 -> 2414
A21: Utilities | B21: =Calculations!C2 -> 140
A22: Groceries | B22: 300
A23: Tranport | B23: 150
A24: Internet | B24: 60
A26: Apartment 3
A27: Expense | B27: Amount
A28: Rent | B28: =Inputs!D13 -> 1945
A29: Utilities | B29: =Calculations!D2 -> 125.5
A30: Groceries | B30: 300
A31: Tranport | B31: 150
A32: Internet | B32: 60
